nunyakata/__init__.py
nunyakata/config.py
nunyakata/services/__init__.py
nunyakata/services/nalo_solutions.py
nunyakata-0.1.2.dist-info/METADATA
nunyakata-0.1.2.dist-info/WHEEL
nunyakata-0.1.2.dist-info/licenses/LICENSE
nunyakata-0.1.2.dist-info/RECORD
