Metadata-Version: 2.4
Name: nunyakata
Version: 0.1.2
Summary: A unified Python package for Ghana-specific services and APIs including Nalo Solutions
Project-URL: Homepage, https://github.com/SeveighTech/nunyakata
Project-URL: Documentation, https://nunyakata.readthedocs.io/
Project-URL: Repository, https://github.com/SeveighTech/nunyakata
Project-URL: Bug Reports, https://github.com/SeveighTech/nunyakata/issues
Project-URL: Source Code, https://github.com/SeveighTech/nunyakata
Project-URL: Changelog, https://nunyakata.readthedocs.io/en/latest/changelog/
Project-URL: Read the Docs, https://nunyakata.readthedocs.io/
Author-email: SeveighTech <info@seveightech.com>
Maintainer-email: SeveighTech <info@seveightech.com>
License: MIT License
License-File: LICENSE
Keywords: api,email,fintech,ghana,mobile-money,nalo,payments,services,sms,unified,ussd
Classifier: Development Status :: 4 - Beta
Classifier: Intended Audience :: Developers
Classifier: Intended Audience :: Financial and Insurance Industry
Classifier: License :: OSI Approved :: MIT License
Classifier: Operating System :: OS Independent
Classifier: Programming Language :: Python :: 3
Classifier: Programming Language :: Python :: 3.8
Classifier: Programming Language :: Python :: 3.9
Classifier: Programming Language :: Python :: 3.10
Classifier: Programming Language :: Python :: 3.11
Classifier: Programming Language :: Python :: 3.12
Classifier: Topic :: Communications :: Chat
Classifier: Topic :: Communications :: Email
Classifier: Topic :: Internet :: WWW/HTTP :: Dynamic Content
Classifier: Topic :: Office/Business :: Financial
Classifier: Topic :: Software Development :: Libraries :: Python Modules
Requires-Python: >=3.8
Requires-Dist: pydantic>=2.0.0
Requires-Dist: requests>=2.25.0
Provides-Extra: all
Requires-Dist: flask>=2.0.0; extra == 'all'
Requires-Dist: python-dotenv>=1.0.0; extra == 'all'
Provides-Extra: dev
Requires-Dist: black>=23.0.0; extra == 'dev'
Requires-Dist: flake8>=6.0.0; extra == 'dev'
Requires-Dist: isort>=5.12.0; extra == 'dev'
Requires-Dist: mypy>=1.0.0; extra == 'dev'
Requires-Dist: pytest-cov>=4.0.0; extra == 'dev'
Requires-Dist: pytest-mock>=3.10.0; extra == 'dev'
Requires-Dist: pytest>=7.0.0; extra == 'dev'
Requires-Dist: requests-mock>=1.10.0; extra == 'dev'
Provides-Extra: env
Requires-Dist: python-dotenv>=1.0.0; extra == 'env'
Provides-Extra: test
Requires-Dist: pytest-cov>=4.0.0; extra == 'test'
Requires-Dist: pytest-mock>=3.10.0; extra == 'test'
Requires-Dist: pytest>=7.0.0; extra == 'test'
Requires-Dist: requests-mock>=1.10.0; extra == 'test'
Provides-Extra: webhook
Requires-Dist: flask>=2.0.0; extra == 'webhook'
